{"stat.pickup.tconstruct.book":3,"stat.drop.akashictome.tome":2,"stat.pickup.minecraft.wooden_slab":2,"stat.mineBlock.tconstruct.seared_tank":1,"stat.leaveGame":3,"stat.pickup.agricraft.crop_sticks":10,"stat.pickup.tconstruct.edible":2,"stat.craftItem.excompressum.compressed_hammer_stone":3,"stat.useItem.chancecubes.chance_cube":5,"stat.mineBlock.extrautils2.compressedcobblestone":222,"stat.pickup.colossalchests.colossal_chest":4,"stat.craftItem.exnihilocreatio.block_dust":81,"stat.pickup.exnihilocreatio.item_ore_aluminum":148,"stat.pickup.xreliquary.mob_ingredient":1,"stat.pickup.minecraft.glass":6,"stat.useItem.minecraft.water_bucket":8,"stat.pickup.exnihilocreatio.block_dust":235,"stat.craftItem.exnihilocreatio.item_ore_platinum":7,"stat.pickup.minecraft.sand":453,"stat.craftItem.minecraft.stone_axe":1,"stat.pickup.minecraft.bucket":3,"stat.pickup.exnihilocreatio.item_pebble":547,"stat.craftItem.tconstruct.casting":1,"stat.useItem.yoyos.shear_yoyo":4,"stat.mineBlock.exnihilocreatio.block_infested_leaves":55,"stat.mineBlock.minecraft.sand":81,"stat.pickup.exnihilocreatio.item_ore_copper":103,"stat.mineBlock.openblocks.grave":2,"stat.useItem.exnihilocreatio.item_material":5,"stat.pickup.exnihilocreatio.item_seed_birch":7,"stat.craftItem.minecraft.wooden_pickaxe":2,"stat.pickup.valkyrielib.guide":3,"stat.pickup.excompressum.heavy_sieve":2,"stat.pickup.minecraft.armor_stand":1,"stat.pickup.exnihilocreatio.block_barrel0":7,"stat.mineBlock.extrautils2.largishchest":1,"stat.pickup.thermalfoundation.material":22,"stat.drop.ceramics.clay_bucket":1,"stat.drop.exnihilocreatio.item_material":80,"stat.mineBlock.chancecubes.chance_cube":10,"stat.furnaceInteraction":45,"stat.pickup.industrialforegoing.pink_slime":2,"stat.craftItem.thermalfoundation.material":22,"stat.craftItem.excompressum.compressed_crook":1,"stat.pickup.minecraft.furnace":5,"stat.pickup.tconstruct.cast":1,"stat.pickup.exnihilocreatio.item_ore_iron":123,"stat.pickup.minecraft.skull":1,"stat.pickup.chancecubes.chance_cube":7,"stat.useItem.minecraft.wheat_seeds":15,"stat.pickup.exnihilocreatio.item_seed_carrot":5,"stat.craftItem.ironchest.iron_chest":1,"stat.pickup.minecraft.pumpkin_seeds":31,"stat.pickup.exnihilocreatio.item_ore_nickel":144,"stat.pickup.minecraft.emerald":7,"stat.craftItem.exnihilocreatio.item_ore_lead":20,"stat.deaths":2,"stat.playOneMinute":294275,"stat.mineBlock.exnihilocreatio.block_andesite_crushed":32,"stat.drop.minecraft.chest":1,"stat.pickup.minecraft.dispenser":18,"stat.useItem.tcomplement.sledge_hammer":265,"stat.pickup.tconstruct.seared":9,"stat.chestOpened":177,"stat.useItem.exnihilocreatio.block_granite_crushed":13,"stat.mineBlock.colossalchests.colossal_chest":4,"stat.useItem.minecraft.stone":29,"stat.pickup.tconstruct.casting":7,"stat.mineBlock.minecraft.dispenser":9,"stat.craftItem.tp.cobblegen_block":1,"stat.pickup.minecraft.detector_rail":1,"stat.craftItem.minecraft.coal":3,"stat.pickup.tconstruct.cast_custom":3,"stat.fallOneCm":8006,"stat.mineBlock.colossalchests.chest_wall":53,"stat.pickup.excompressum.compressed_crook":1,"stat.pickup.enderio.item_alloy_ingot":3,"stat.pickup.minecraft.carrot":8,"stat.pickup.minecraft.melon_seeds":36,"stat.crouchOneCm":16493,"stat.mineBlock.minecraft.chest":13,"stat.craftItem.minecraft.chest":17,"stat.craftItem.minecraft.iron_ingot":15,"stat.useItem.minecraft.iron_hoe":9,"stat.pickup.xreliquary.glowing_water":1,"stat.craftItem.tconstruct.pattern":18,"stat.pickup.minecraft.feather":2,"stat.craftItem.teslacorelib.gear_wood":1,"stat.useItem.minecraft.furnace":3,"stat.craftItem.tconstruct.materials":120,"stat.useItem.excompressum.compressed_crook":58,"stat.pickup.minecraft.dye":118,"stat.pickup.exnihilocreatio.item_ore_gold":141,"stat.pickup.minecraft.planks":6,"stat.pickup.minecraft.wheat_seeds":127,"stat.mineBlock.minecraft.gravel":196,"stat.useItem.minecraft.stone_pickaxe":407,"stat.craftItem.tconstruct.seared_tank":1,"stat.pickup.openblocks.technicolor_glasses":1,"stat.mineBlock.minecraft.dirt":5,"stat.pickup.exnihilocreatio.item_mesh":9,"stat.useItem.minecraft.torch":1,"stat.mineBlock.exnihilocreatio.block_dust":1,"stat.pickup.exnihilocreatio.item_seed_darkoak":7,"stat.useItem.minecraft.log":1,"stat.useItem.minecraft.cobblestone":252,"stat.craftItem.extrautils2.compressedgravel":211,"stat.craftItem.minecraft.crafting_table":4,"stat.useItem.minecraft.gravel":178,"stat.craftItem.ceramics.clay_bucket":1,"stat.pickup.minecraft.iron_hoe":2,"stat.pickup.minecraft.log":332,"stat.craftItem.tp.wooden_shears":22,"stat.craftItem.exnihilocreatio.block_sieve":2,"stat.pickup.minecraft.chicken":1,"stat.pickup.minecraft.sapling":117,"stat.craftItem.colossalchests.colossal_chest":1,"stat.pickup.minecraft.apple":10,"stat.useItem.exnihilocreatio.block_barrel0":8,"stat.pickup.minecraft.banner":1,"stat.craftItem.tconstruct.smeltery_controller":1,"stat.mineBlock.minecraft.tripwire_hook":9,"stat.pickup.yoyos.shear_yoyo":1,"stat.craftItem.minecraft.bucket":1,"stat.craftItem.minecraft.planks":561,"stat.mineBlock.minecraft.log":194,"stat.pickup.forestry.book_forester":3,"stat.drop.tconstruct.edible":1,"stat.mineBlock.exnihilocreatio.block_crucible":1,"stat.pickup.exnihilocreatio.item_seed_acacia":4,"stat.sneakTime":11868,"stat.pickup.exnihilocreatio.block_sieve":2,"stat.mineBlock.extrautils2.compressedgravel":34,"stat.pickup.minecraft.stone_slab":7,"stat.craftItem.minecraft.cobblestone":80,"stat.pickup.minecraft.chest":14,"stat.pickup.minecraft.tripwire_hook":18,"stat.useItem.exnihilocreatio.hammer_gold":64,"stat.craftItem.ceramics.unfired_clay":15,"stat.mineBlock.minecraft.cobblestone":777,"stat.pickup.minecraft.stone_pickaxe":1,"stat.pickup.minecraft.flint":434,"stat.craftItem.tconstruct.faucet":1,"stat.pickup.exnihilocreatio.item_ore_lead":145,"stat.craftItem.extrautils2.compressedcobblestone":222,"stat.swimOneCm":2778,"stat.climbOneCm":20430,"stat.pickup.lootbags.itemlootbag":2,"stat.useItem.colossalchests.chest_wall":78,"stat.useItem.minecraft.dirt":10,"stat.useItem.minecraft.stone_slab2":148,"stat.useItem.agricraft.crop_sticks":7,"stat.craftItem.minecraft.furnace":3,"stat.pickup.tp.cobblegen_block":1,"stat.craftItem.minecraft.stone_pickaxe":4,"stat.pickup.minecraft.cobblestone":835,"stat.pickup.exnihilocreatio.item_seed_cactus":4,"stat.pickup.minecraft.clay":169,"stat.flyOneCm":2167,"stat.pickup.tp.wooden_shears":5,"stat.pickup.harvestcraft.toastsandwichitem":3,"stat.useItem.extrautils2.compressedgravel":28,"stat.craftItem.minecraft.wooden_slab":24,"stat.craftItem.extrautils2.compresseddirt":8,"stat.pickup.extrautils2.compressedgravel":1,"stat.timeSinceDeath":21504,"stat.useItem.minecraft.wooden_slab":7,"stat.craftItem.colossalchests.chest_wall":32,"stat.useItem.exnihilocreatio.crook_bone":256,"stat.craftItem.tconstruct.seared":36,"stat.drop.minecraft.dirt":8,"stat.pickup.exnihilocreatio.item_seed_oak":5,"stat.drop.forestry.book_forester":2,"stat.pickup.botania.manabottle":1,"stat.craftItem.tconstruct.soil":192,"stat.pickup.minecraft.string":128,"stat.pickup.exnihilocreatio.item_seed_jungle":8,"stat.pickup.tconstruct.smeltery_controller":1,"stat.mineBlock.minecraft.ladder":53,"stat.craftItem.exnihilocreatio.hammer_stone":27,"stat.pickup.excompressum.compressed_hammer_stone":1,"stat.craftItem.minecraft.stone_slab2":1,"stat.pickup.exnihilocreatio.item_ore_aluminium":144,"stat.craftItem.tconstruct.tooltables":10,"stat.craftItem.excompressum.heavy_sieve":1,"stat.sprintOneCm":2416,"stat.pickup.actuallyadditions.item_misc":10,"stat.mineBlock.minecraft.stone_slab":1,"stat.craftItem.minecraft.stick":196,"stat.useItem.minecraft.stone_slab":7,"stat.craftItem.agricraft.crop_sticks":8,"stat.pickup.exnihilocreatio.item_material":179,"stat.craftItem.minecraft.stone":46,"stat.mineBlock.exnihilocreatio.block_granite_crushed":15,"stat.useItem.minecraft.diamond_pickaxe":132,"stat.useItem.minecraft.carrot":3,"stat.useItem.excompressum.compressed_hammer_stone":388,"stat.craftItem.minecraft.clay_ball":32,"stat.pickup.exnihilocreatio.hammer_gold":2,"stat.useItem.extrautils2.compressedsand":14,"stat.drop":17,"stat.craftItem.excompressum.wooden_crucible":1,"stat.useItem.tconstruct.seared":33,"stat.useItem.minecraft.ladder":60,"stat.mineBlock.extrautils2.compressedsand":17,"stat.killEntity.Zombie":1,"stat.pickup.opencomputers.tool":1,"stat.craftItem.exnihilocreatio.item_ore_copper":18,"stat.pickup.akashictome.tome":3,"stat.diveOneCm":91,"stat.pickup.minecraft.wheat":18,"stat.useItem.exnihilocreatio.crook_wood":128,"stat.pickup.tconstruct.tooltables":5,"stat.craftItem.minecraft.ladder":12,"stat.pickup.exnihilocreatio.block_crucible":1,"stat.pickup.minecraft.gravel":2197,"stat.useItem.extrautils2.compressedcobblestone":210,"stat.mineBlock.tconstruct.smeltery_controller":1,"stat.drop.valkyrielib.guide":2,"stat.useItem.minecraft.apple":10,"stat.useItem.exnihilocreatio.block_dust":1,"stat.pickup.exnihilocreatio.item_ore_tin":131,"stat.pickup.exnihilocreatio.item_seed_sugarcane":6,"stat.craftItem.exnihilocreatio.block_crucible":4,"stat.jump":259,"stat.useItem.minecraft.sand":77,"stat.pickup.minecraft.coal":189,"stat.pickup.exnihilocreatio.block_granite_crushed":15,"stat.pickup.minecraft.iron_ingot":4,"stat.pickup.tconstruct.seared_tank":1,"stat.useItem.exnihilocreatio.item_seed_carrot":4,"stat.useItem.minecraft.stone_axe":60,"stat.pickup.minecraft.gunpowder":10,"stat.craftItem.minecraft.torch":4,"stat.pickup.minecraft.dirt":148,"stat.mineBlock.excompressum.wooden_crucible":1,"stat.useItem.minecraft.sapling":33,"stat.craftItem.exnihilocreatio.item_ore_iron":24,"stat.mineBlock.tconstruct.tooltables":5,"stat.pickup.minecraft.leaves":994,"stat.pickup.minecraft.cookie":8,"stat.pickup.exnihilocreatio.item_ore_platinum":45,"stat.pickup.exnihilocreatio.item_seed_spruce":5,"stat.damageTaken":570,"stat.mineBlock.minecraft.furnace":5,"stat.dispenserInspected":1,"stat.useItem.minecraft.wooden_pickaxe":118,"stat.mineBlock.minecraft.sapling":1,"stat.pickup.mysticalagriculture.crafting":2,"stat.pickup.minecraft.reeds":12,"stat.pickup.exnihilocreatio.item_ore_silver":127,"stat.pickup.exnihilocreatio.item_seed_potato":9,"stat.pickup.tconstruct.materials":48,"stat.entityKilledBy.Zombie":1,"stat.pickup.extrautils2.largishchest":1,"stat.craftItem.extrautils2.compressedsand":31,"stat.craftItem.exnihilocreatio.crook_wood":8,"stat.damageDealt":233,"stat.craftItem.minecraft.glass":4,"stat.useItem.exnihilocreatio.item_seed_sugarcane":1,"stat.mineBlock.exnihilocreatio.block_barrel0":7,"stat.mineBlock.excompressum.heavy_sieve":2,"stat.craftItem.minecraft.stone_slab":12,"stat.walkOneCm":492148,"stat.craftItem.excompressum.compressed_block":15,"stat.useItem.minecraft.chest":4,"stat.craftItem.tconstruct.smeltery_io":1,"stat.pickup.minecraft.stick":2,"stat.pickup.minecraft.clay_ball":3,"stat.useItem.minecraft.lava_bucket":2,"stat.drop.questbook.itemquestbook":1,"stat.pickup.questbook.itemquestbook":2,"stat.craftItem.exnihilocreatio.item_ore_nickel":21,"stat.pickup.randomthings.summoningpendulum":2,"stat.useItem.exnihilocreatio.block_andesite_crushed":30,"stat.pickup.exnihilocreatio.block_andesite_crushed":64,"stat.pickup.openblocks.info_book":1,"stat.pickup.minecraft.stone":15,"stat.useItem.harvestcraft.toastsandwichitem":2,"stat.useItem.minecraft.leaves":3,"stat.pickup.tcomplement.sledge_hammer":2,"stat.pickup.minecraft.ladder":55,"stat.craftItem.exnihilocreatio.item_ore_tin":20,"stat.killEntity.Chicken":1,"stat.craftItem.exnihilocreatio.block_barrel0":5,"stat.mobKills":2,"stat.pickup.excompressum.wooden_crucible":2,"stat.craftItem.exnihilocreatio.item_ore_gold":23,"stat.pickup.minecraft.diamond":6,"stat.mineBlock.minecraft.leaves":1648,"stat.pickup.minecraft.torch":3,"stat.craftItem.exnihilocreatio.item_ore_aluminium":18,"stat.mineBlock.tconstruct.seared":3,"stat.mineBlock.tconstruct.casting":7,"stat.drop.exnihilocreatio.item_mesh":1,"stat.pickup.minecraft.lava_bucket":1,"stat.craftItem.exnihilocreatio.item_ore_silver":18,"stat.mineBlock.tp.cobblegen_block":1,"stat.craftItem.exnihilocreatio.item_mesh":6,"stat.craftItem.exnihilocreatio.item_ore_aluminum":16,"stat.mineBlock.exnihilocreatio.block_sieve":2,"stat.mineBlock.minecraft.stone":31,"stat.drop.tconstruct.book":2,"stat.pickup.colossalchests.chest_wall":53}